{"web":{"client_id":"115873108956-1d40guadv4vh9nluqsaiktgt7ughi91b.apps.googleusercontent.com","project_id":"django-oauth-401206","auth_uri":"https://accounts.google.com/o/oauth2/auth","token_uri":"https://oauth2.googleapis.com/token","auth_provider_x509_cert_url":"https://www.googleapis.com/oauth2/v1/certs","client_secret":"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","redirect_uris":["http://127.0.0.1:800","http://127.0.0.1:800/accounts/google/login/callback","https://erp.demfirat.com","https://erp.demfirat.com/accounts/google/login/callback"]}}